robinson_nlp2_y2d/dist/robinson_nlp2_y2d-1.0.0-py3-none-any.whl
robinson_nlp2_y2d/dist/robinson_nlp2_y2d-1.0.0.tar.gz
robinson_nlp2_y2d/dist/robinson_nlp2_y2d-1.0.1-py3-none-any.whl
robinson_nlp2_y2d/dist/robinson_nlp2_y2d-1.0.1.tar.gz
robinson_nlp2_y2d/poetry.lock
robinson_nlp2_y2d/pyproject.toml
robinson_nlp2_y2d/readme.md
robinson_nlp2_y2d/robinson_nlp2_y2d/__init__.py
robinson_nlp2_y2d-1.0.3.dist-info/LICENSE
robinson_nlp2_y2d-1.0.3.dist-info/METADATA
robinson_nlp2_y2d-1.0.3.dist-info/WHEEL
robinson_nlp2_y2d-1.0.3.dist-info/RECORD
