Metadata-Version: 2.1
Name: robinson_NLP2_y2d
Version: 1.0.3
Summary: 
Author: Leonard Mohnansky
Author-email: 220201@buas.nl
Requires-Python: >=3.9,<3.10
Classifier: Programming Language :: Python :: 3
Classifier: Programming Language :: Python :: 3.9
Requires-Dist: accelerate (>=0.31.0,<0.32.0)
Requires-Dist: azureml (>=0.2.7,<0.3.0)
Requires-Dist: azureml-core (>=1.56.0,<2.0.0)
Requires-Dist: azureml-defaults (>=1.56.0.post1,<2.0.0)
Requires-Dist: azureml-sdk (>=1.56.0,<2.0.0)
Requires-Dist: deep_translator (>=1.11.4,<2.0.0)
Requires-Dist: fastapi (>=0.111.0,<0.112.0)
Requires-Dist: flake8 (>=7.1.1,<8.0.0)
Requires-Dist: httpx (>=0.27.0,<0.28.0)
Requires-Dist: inquirer (>=3.2.4,<4.0.0)
Requires-Dist: keras (==2.10.0)
Requires-Dist: llvmlite (>=0.43.0,<0.44.0)
Requires-Dist: matplotlib (>=3.8.4,<4.0.0)
Requires-Dist: mlflow (>=2.14.1,<3.0.0)
Requires-Dist: more-itertools (>=10.2.0,<11.0.0)
Requires-Dist: mypy (>=1.11.1,<2.0.0)
Requires-Dist: networkx (==3.2.1)
Requires-Dist: nltk (>=3.8.1,<4.0.0)
Requires-Dist: numba (>=0.60.0,<0.61.0)
Requires-Dist: numpy (==1.23.5)
Requires-Dist: pandas (>=2.2.2,<3.0.0)
Requires-Dist: pandas-stubs (>=2.2.2.240807,<3.0.0.0)
Requires-Dist: pre-commit (>=3.8.0,<4.0.0)
Requires-Dist: protobuf (>=3.9.2,<3.20)
Requires-Dist: pytest (>=8.3.2,<9.0.0)
Requires-Dist: pytest-cov (>=5.0.0,<6.0.0)
Requires-Dist: scikit-learn (>=1.4.2,<2.0.0)
Requires-Dist: seaborn (>=0.13.2,<0.14.0)
Requires-Dist: spacy (>=3.7.4,<4.0.0)
Requires-Dist: sphinx (>=7,<8)
Requires-Dist: sympy (==1.12.1)
Requires-Dist: tensorboard (>=2.10,<2.16)
Requires-Dist: tensorflow (==2.10.0)
Requires-Dist: tensorflow-estimator (==2.10.0)
Requires-Dist: tensorflow-io-gcs-filesystem (==0.31.0)
Requires-Dist: textblob (>=0.18.0.post0,<0.19.0)
Requires-Dist: tiktoken (==0.7.0)
Requires-Dist: toolz (>=0.12.1,<0.13.0)
Requires-Dist: transformers (==4.37.2)
Requires-Dist: uvicorn (>=0.30.1,<0.31.0)
